pyproto/__init__.py
pyproto/converter.py
python_proto_converter-1.0.2.dist-info/licenses/LICENSE
python_proto_converter-1.0.2.dist-info/METADATA
python_proto_converter-1.0.2.dist-info/WHEEL
python_proto_converter-1.0.2.dist-info/top_level.txt
python_proto_converter-1.0.2.dist-info/RECORD
